grand_challenge_metrics/__init__.py
grand_challenge_metrics/annotations.py
grand_challenge_metrics/roc.py
grand_challenge_metrics/scorers.py
grand_challenge_metrics/stats.py
grand_challenge_metrics-0.6.0.dist-info/licenses/LICENSE
grand_challenge_metrics-0.6.0.dist-info/METADATA
grand_challenge_metrics-0.6.0.dist-info/WHEEL
grand_challenge_metrics-0.6.0.dist-info/top_level.txt
grand_challenge_metrics-0.6.0.dist-info/RECORD
