Metadata-Version: 2.4
Name: grand-challenge-metrics
Version: 0.6.0
Summary: useful functions for evaluating machine learning models in the context of medical imaging
Author: James Meakin
License: MIT
Project-URL: repository, https://github.com/DIAGNijmegen/rse-grand-challenge-metrics
Classifier: Development Status :: 3 - Alpha
Classifier: Intended Audience :: Developers
Classifier: Intended Audience :: Healthcare Industry
Classifier: Natural Language :: English
Requires-Python: <4.0,>=3.10
License-File: LICENSE
Requires-Dist: scipy
Requires-Dist: numpy
Requires-Dist: scikit-learn
Dynamic: license-file
